<Entry>
	<Name>CRIME</Name> 
	<ExtendedName>**C**ompression **R**atio **I**nfo-leak **M**ass **E**xploitation</ExtendedName>
	<CVE>2012-4929</CVE>
	<CVSS3>9.1 (Critical)</CVSS3> <!-- AV:N/AC:L/PR:N/UI:N/S:U/C:H/I:H/A:N -->
	<Description>By exploiting the information leakage provided by DEFLATE (compression algorithm), an attacker is able to retrieve the session cookie. In particular, the attacker guesses parts of the cookie, injects them in a valid client packet and analyzes the server's response. Thanks to the properties of a DEFLATE output, if the server's response is bigger than an untouched packet, then the guess is wrong.</Description> 
	<Mitigation>
		<Textual>Disable the TLS compression mechanism.</Textual>
		<Snippet>
			<apache>1. open your Apache configuration file (default: */etc/apache2/sites-available/default-ssl.conf*);
2. search for the line starting with: **SSLCompression**
   - if found, change the value to **off**;
   - if not, add the line `SSLCompression off` within the file.

N.B. restart the server by typing: `sudo service apache2 restart`.</apache>
			<nginx>SSL compression is turned off by default in nginx 1.1.6+/1.0.9+ (if OpenSSL 1.0.0+ used) and nginx 1.3.2+/1.2.2+ (if older versions of OpenSSL are used).

- If you are using al earlier version of nginx or OpenSSL and your distro has not backported this option then you need to 
	1. **update to the last version** or
	2. recompile OpenSSL without ZLIB support.
			</nginx>
		</Snippet>
	</Mitigation>
</Entry>
<!-- https://www.acunetix.com/vulnerabilities/web/crime-ssl-tls-attack/ -->
<!-- https://www.nccgroup.trust/us/about-us/newsroom-and-events/blog/2012/september/details-on-the-crime-attack/ -->
